Bcryptify/GenKeyAesGcm.py
Bcryptify/IAsymmetricCipher.py
Bcryptify/IRsaKeyManager.py
Bcryptify/ISymmetricCipher.py
Bcryptify/RsaKeyManager.py
Bcryptify/__init__.py
Bcryptify/aes_gcm.py
Bcryptify/rsa.py
bcryptify-1.1.2.dist-info/licenses/LICENSE
bcryptify-1.1.2.dist-info/METADATA
bcryptify-1.1.2.dist-info/WHEEL
bcryptify-1.1.2.dist-info/top_level.txt
bcryptify-1.1.2.dist-info/RECORD
