Metadata-Version: 2.4
Name: bcryptify
Version: 1.1.2
Summary: Bcryptify is a modern and elegant Python library designed to simplify the use of cryptographic algorithms, while adhering to SOLID principles to ensure clean, extensible, and maintainable code.
Home-page: https://github.com/Tina-1300/Bcryptify
Author: Tina
Author-email: tina.xytrfgthuji1348@gmail.com
License: MIT
Classifier: Programming Language :: Python :: 3
Classifier: License :: OSI Approved :: MIT License
Classifier: Operating System :: OS Independent
Classifier: Intended Audience :: Developers
Classifier: Topic :: Security :: Cryptography
Classifier: Topic :: Software Development :: Libraries
Requires-Python: >=3.13.0
License-File: LICENSE
Dynamic: license-file
